{
  "address": "მისამართი",
  "telephone": "ტელეფონი",
  "fax": "ფაქსი",
  "about": {
    "title": "ჩვენ შესახებ",
    "team": "გუნდი"
  },
  "drug_info": {
    "title": "ნარკო-ინფო"
  },
  "news": {
    "title": "სიახლეები"
  },
  "contact": {
    "title": "კონტაქტი"
  },
  "page404": {
    "title": "404",
    "text": "გვერდი არ არსებობს"
  },
  "home": {
    "title": "მთავარი"
  },
  "projects": {
    "title": "პროექტები"
  },
  "publications": {
    "title": "პუბლიკაციები",
    "kaLink": "ქართული ვერსია",
    "enLink": "ინგლისური ვერსია"
  },
  "scientific_publications": {
    "title": "სამეცნიერო პუბლიკაციები"
  },
  "technical_reports": {
    "title": "ტექნიკური ანგარიშები"
  },
  "drug_situation_in_georgia": {
    "title": "ნარკოვითარება საქართველოში"
  },
  "current": "მიმდინარე",
  "copyright": "\"ალტერნატივა ჯორჯია\" საავტორო უფლებები დაცულია",
  "months": {
    "01": "იანვარი",
    "02": "თებერვალი",
    "03": "მარტი",
    "04": "აპრილი",
    "05": "მაისი",
    "06": "ივნისი",
    "07": "ივლისი",
    "08": "აგვისტო",
    "09": "სექტემბერი",
    "10": "ოქტომბერი",
    "11": "ნოემბერი",
    "12": "დეკემბერი"
  }
}

